LICENSE
README.md
pysdf/__init__.py
pysdf/base.py
pysdf/sdf_types.py
python_sdformat-0.4.0.dist-info/LICENSE
python_sdformat-0.4.0.dist-info/WHEEL
python_sdformat-0.4.0.dist-info/METADATA
python_sdformat-0.4.0.dist-info/RECORD
