Metadata-Version: 2.1
Name: python-sdformat
Version: 0.4.0
Summary: Python Parser for SDFormat files.
Home-page: https://github.com/FirefoxMetzger/python-sdformat
License: BSD-2-Clause
Author: FirefoxMetzger
Author-email: sebastian@wallkoetter.net
Requires-Python: >=3.7,<4.0
Classifier: License :: OSI Approved :: BSD License
Classifier: Programming Language :: Python :: 3
Classifier: Programming Language :: Python :: 3.10
Classifier: Programming Language :: Python :: 3.7
Classifier: Programming Language :: Python :: 3.8
Classifier: Programming Language :: Python :: 3.9
Requires-Dist: lxml (>=4.8.0,<5.0.0)
Requires-Dist: numpy (>=1.0,<2.0)
Project-URL: Repository, https://github.com/FirefoxMetzger/python-sdformat
